finegist/__init__.py
finegist/budget.py
finegist/expense_tracker.py
finegist/financial_goal_planner.py
finegist/investment_portfolio.py
finegist/loan_repayment_calculator.py
finegist/net_worth_calculator.py
finegist/savings_calculator.py
finegist-0.0.1.dist-info/METADATA
finegist-0.0.1.dist-info/WHEEL
finegist-0.0.1.dist-info/top_level.txt
finegist-0.0.1.dist-info/RECORD
